pycadence/__init__.py
pycadence/pycadence.py
pycadence/utils.py
CadenceConnector-0.2.3.dist-info/LICENSE
CadenceConnector-0.2.3.dist-info/METADATA
CadenceConnector-0.2.3.dist-info/WHEEL
CadenceConnector-0.2.3.dist-info/top_level.txt
CadenceConnector-0.2.3.dist-info/RECORD
