Metadata-Version: 2.1
Name: CadenceConnector
Version: 0.2.3
Summary: A python SDK for running simulation and reading data from Ocean Cadence
Home-page: https://github.com/joetho786/PyCadence
Author: joetho786
Author-email: thomas.2@iitj.ac.in
Classifier: Programming Language :: Python :: 3
Classifier: License :: OSI Approved :: MIT License
Classifier: Operating System :: Unix
Requires-Python: >=3.6
License-File: LICENSE
